pymodoro/__init__.py
pymodoro/__main__.py
pymodoro/db.py
pymodoro/enums.py
pymodoro/events.py
pymodoro/menus.py
pymodoro/pymodoro.tcss
pymodoro/pymodoro_app.py
pymodoro/themes.py
pymodoro/timer.py
pymodoro_tui-0.1.6.dist-info/METADATA
pymodoro_tui-0.1.6.dist-info/WHEEL
pymodoro_tui-0.1.6.dist-info/entry_points.txt
pymodoro_tui-0.1.6.dist-info/licenses/LICENSE
pymodoro_tui-0.1.6.dist-info/RECORD
