Metadata-Version: 2.4
Name: pymodoro-tui
Version: 0.1.6
Summary: Pomodoro Timer in your terminal
Author-email: alexanderchainsaw <alexanderkolesov.contact@gmail.com>
License-Expression: MIT
License-File: LICENSE
Requires-Python: >=3.13
Requires-Dist: textual>=1.0.0
Requires-Dist: xdg-base-dirs>=6.0.2
